ifconfig.cpython-39-x86_64-linux-gnu.so
ifconfig-0.0.2.dist-info/LICENSE
ifconfig-0.0.2.dist-info/WHEEL
ifconfig-0.0.2.dist-info/RECORD
ifconfig-0.0.2.dist-info/METADATA
ifconfig-0.0.2.dist-info/top_level.txt
