Metadata-Version: 2.1
Name: ifconfig
Version: 0.0.2
Summary: configure a network interface
Author: skrab-sah
Author-email: skrab.sah@gmail.com
Classifier: Operating System :: POSIX :: Linux
Classifier: License :: OSI Approved :: MIT License
License-File: LICENSE
